{
	"storyName": "Your New Week",
	"hideFreeplay": false,
	"weekBackground": "stage",
	"freeplayColor": [
		146,
		113,
		253
	],
	"weekBefore": "tutorial",
	"startUnlocked": true,
	"weekCharacters": [
		"dad",
		"bf",
		"gf"
	],
	"songs": [
		[
			"parched",
			"icon-heaven",
			[
				46,
				133,
				255
			]
		],
		[
			"veiled",
			"heaven",
			[
				46,
				133,
				255
			]
		],
		[
			"snared",
			"heaven_snake",
			[
				46,
				133,
				255
			]
		]
	],
	"hideStoryMode": false,
	"weekName": "Custom Week"
}